ouparams/__init__.py
ouparams/ouparams.py
ouparams-0.0.1.dist-info/LICENSE
ouparams-0.0.1.dist-info/METADATA
ouparams-0.0.1.dist-info/WHEEL
ouparams-0.0.1.dist-info/top_level.txt
ouparams-0.0.1.dist-info/RECORD
